confs/__init__.py
confs/__main__.py
confs/_cli.py
confs/_const.py
confs/_core.py
confs-1.0.0.dist-info/entry_points.txt
confs-1.0.0.dist-info/LICENSE
confs-1.0.0.dist-info/WHEEL
confs-1.0.0.dist-info/METADATA
confs-1.0.0.dist-info/RECORD
