Metadata-Version: 2.1
Name: confs
Version: 1.0.0
Summary: CLI tool that lists tools for which the given project has configuration files.
Home-page: https://github.com/orsinium-labs/confs
License: MIT
Keywords: cli,tools,configs
Author: Gram
Author-email: gram@orsinium.dev
Requires-Python: >=3.6
Classifier: Development Status :: 5 - Production/Stable
Classifier: Intended Audience :: Developers
Classifier: License :: OSI Approved :: MIT License
Classifier: Programming Language :: Python
Classifier: Topic :: Software Development
Classifier: Topic :: Software Development :: Libraries :: Python Modules
Classifier: Topic :: Software Development :: Quality Assurance
